scriptforge-stubs/__init__.pyi
scriptforge-stubs/py.typed
types_scriptforge-7.6.0.1.dist-info/LICENSE
types_scriptforge-7.6.0.1.dist-info/METADATA
types_scriptforge-7.6.0.1.dist-info/WHEEL
types_scriptforge-7.6.0.1.dist-info/RECORD
