Metadata-Version: 2.1
Name: types-scriptforge
Version: 7.6.0.1
Summary: Type annotations for LibreOffice API
Home-page: https://github.com/Amourspirit/python-types-scriptforge
License: Apache-2.0
Keywords: libreoffice,openoffice,scriptforge,typings,uno,ooouno,pyuno
Author: :Barry-Thomas-Paul: Moss
Author-email: bigbytetech@gmail.com
Requires-Python: >=3.7,<4.0
Classifier: Environment :: Other Environment
Classifier: Intended Audience :: Developers
Classifier: License :: OSI Approved :: Apache Software License
Classifier: Operating System :: OS Independent
Classifier: Programming Language :: Python :: 3
Classifier: Programming Language :: Python :: 3.7
Classifier: Programming Language :: Python :: 3.8
Classifier: Programming Language :: Python :: 3.9
Classifier: Programming Language :: Python :: 3.10
Classifier: Programming Language :: Python :: 3.11
Classifier: Topic :: Office/Business
Classifier: Typing :: Typed
Requires-Dist: types-uno-script (>=0.1.1)
Requires-Dist: types-unopy (>=1.0.1)
Project-URL: Repository, https://github.com/Amourspirit/python-types-scriptforge
